.bumpversion.cfg
.gitignore
CONTRIBUTING.md
LICENSE
MANIFEST.in
README.md
requirements.txt
setup.py
test_requirements.txt
dashdataframe/__init__.py
dashdataframe/dashdf_layouts.py
dashdataframe.egg-info/PKG-INFO
dashdataframe.egg-info/SOURCES.txt
dashdataframe.egg-info/dependency_links.txt
dashdataframe.egg-info/requires.txt
dashdataframe.egg-info/top_level.txt
examples/fly_regions.h5
examples/testdash.py