Metadata-Version: 1.0
Name: dashdataframe
Version: 0.2.1
Summary: An simplified interface for making dash apps to explore multi-dimensional dataframes with custom link integration and filtering.
Home-page: https://github.com/AllenInstitute/DashDataFrame.git
Author: Leila Elabbady, Forrest Collman, Melissa Hendershott
Author-email: leilae@alleninstitute.org
License: UNKNOWN
Platform: UNKNOWN
